{
  "project_info": {
    "project_number": "92715321903",
    "project_id": "remedic-23769",
    "storage_bucket": "remedic-23769.firebasestorage.app"
  },
  "client": [
    {
      "client_info": {
        "mobilesdk_app_id": "1:92715321903:android:ac865b49d84a33bccb94da",
        "android_client_info": {
          "package_name": "com.example.remedic"
        }
      },
      "oauth_client": [],
      "api_key": [
        {
          "current_key": "AIzaSyCvp7UsyyyXwAEWne1XfqIyy1FNIUsMe2A"
        }
      ],
      "services": {
        "appinvite_service": {
          "other_platform_oauth_client": []
        }
      }
    }
  ],
  "configuration_version": "1"
}